aspectratiox/__init__.py
aspectratiox/main.py
aspectratiox-1.0.dist-info/LICENSE
aspectratiox-1.0.dist-info/METADATA
aspectratiox-1.0.dist-info/WHEEL
aspectratiox-1.0.dist-info/entry_points.txt
aspectratiox-1.0.dist-info/top_level.txt
aspectratiox-1.0.dist-info/RECORD
