Metadata-Version: 2.1
Name: aspectratiox
Version: 1.0
Summary: Aspect ratio conversion tool for images using ffmpeg.
Home-page: https://x.com/Lanaev0li
Author: Avinion Group
Author-email: shizofrin@gmail.com
License: MIT
Classifier: Programming Language :: Python :: 3
Classifier: License :: OSI Approved :: MIT License
Classifier: Operating System :: OS Independent
License-File: LICENSE
